.clang-format
.gitignore
.ycm_extra_conf.py
LICENSE
MANIFEST.in
README.md
RELEASENOTES.txt
VERSION.txt
pyproject.toml
setup.py
CUDA/CMakeLists.txt
CUDA/bin/gtest_options
CUDA/bin/run_cpu_filtered_unit_test.cmd
CUDA/bin/run_cuda_memcheck
CUDA/bin/run_gpu_filtered_unit_test.cmd
CUDA/bin/cvp/Gridding3D.cvp
CUDA/bin/cvp/README
CUDA/build/configure_double_prec
CUDA/build/configure_single_prec
CUDA/cmake_modules/FindGPUNUFFT.cmake
CUDA/doc/CMakeLists.txt
CUDA/doc/Doxyfile
CUDA/doc/mainpage.dox
CUDA/inc/balanced_gpuNUFFT_operator.hpp
CUDA/inc/balanced_operator.hpp
CUDA/inc/config.hpp
CUDA/inc/config.hpp.cmake
CUDA/inc/cuda_utils.cuh
CUDA/inc/cuda_utils.hpp
CUDA/inc/cufft_config.hpp
CUDA/inc/cufft_config.hpp.cmake
CUDA/inc/gpuNUFFT_cpu.hpp
CUDA/inc/gpuNUFFT_kernels.hpp
CUDA/inc/gpuNUFFT_operator.hpp
CUDA/inc/gpuNUFFT_operator_factory.hpp
CUDA/inc/gpuNUFFT_types.hpp
CUDA/inc/gpuNUFFT_utils.hpp
CUDA/inc/matlab_helper.h
CUDA/inc/precomp_kernels.hpp
CUDA/inc/precomp_utils.hpp
CUDA/src/CMakeLists.txt
CUDA/src/balanced_gpuNUFFT_operator.cpp
CUDA/src/gpuNUFFT_operator.cpp
CUDA/src/gpuNUFFT_operator_factory.cpp
CUDA/src/gpuNUFFT_utils.cpp
CUDA/src/cpu/gpuNUFFT_cpu.cpp
CUDA/src/gpu/CMakeLists.txt
CUDA/src/gpu/precomp_kernels.cu
CUDA/src/gpu/std_gpuNUFFT_kernels.cu
CUDA/src/gpu/atomic/CMakeLists.txt
CUDA/src/gpu/atomic/atomic_gpuNUFFT.cu
CUDA/src/gpu/atomic/atomic_gpuNUFFT_kernels.cu
CUDA/src/gpu/matlab/CMakeLists.txt
CUDA/src/gpu/matlab/gpuNUFFT_adj.cpp
CUDA/src/gpu/matlab/gpuNUFFT_forw.cpp
CUDA/src/gpu/matlab/gpuNUFFT_operator_matlabfactory.cpp
CUDA/src/gpu/matlab/gpuNUFFT_operator_matlabfactory.hpp
CUDA/src/gpu/matlab/precomputation/CMakeLists.txt
CUDA/src/gpu/matlab/precomputation/gpuNUFFT_precomp.cpp
CUDA/src/gpu/python/CMakeLists.txt
CUDA/src/gpu/python/gpuNUFFT_operator_python_factory.cpp
CUDA/test/CMakeLists.txt
CUDA/test/cpu/CMakeLists.txt
CUDA/test/cpu/gpuNUFFT_kernel_tests.cpp
CUDA/test/cpu/gpuNUFFT_operator_factory_tests.cpp
gpuNUFFT.egg-info/PKG-INFO
gpuNUFFT.egg-info/SOURCES.txt
gpuNUFFT.egg-info/dependency_links.txt
gpuNUFFT.egg-info/not-zip-safe
gpuNUFFT.egg-info/top_level.txt
