Metadata-Version: 2.4
Name: gpuNUFFT
Version: 0.10.6
Summary: gpuNUFFT - An open source GPU Library for 3D Gridding and NUFFT
License-File: LICENSE
Dynamic: license-file
Dynamic: summary
